setup.cfg
setup.py
steamCLI/__init__.py
steamCLI/__main__.py
steamCLI/colors.py
steamCLI/config.py
steamCLI/console.py
steamCLI/resources.ini
steamCLI/results.py
steamCLI/steamapp.py
steamCLI/utils.py
steamCLI.egg-info/PKG-INFO
steamCLI.egg-info/SOURCES.txt
steamCLI.egg-info/dependency_links.txt
steamCLI.egg-info/entry_points.txt
steamCLI.egg-info/requires.txt
steamCLI.egg-info/top_level.txt
test/__init__.py
test/test_config.py
test/test_console.py
test/test_results.py
test/test_steamapp.py
test/test_utils.py