Metadata-Version: 1.0
Name: steamCLI
Version: 1.0.5
Summary: Find price information about games on Steam from the command line.
Home-page: https://github.com/vilisimo/steamCLI
Author: vilisimo
Author-email: vilisimo@gmail.com
License: MIT License
Platform: UNKNOWN
